[{"PositionX":568,"PositionY":497,"LeftButtonDown":false,"RightButtonDown":false,"MiddleButtonDown":false,"EventType":0,"EventTimeInTicks":637195298135181954},{"PositionX":569,"PositionY":497,"LeftButtonDown":false,"RightButtonDown":false,"MiddleButtonDown":false,"EventType":0,"EventTimeInTicks":637195298141601935},{"PositionX":569,"PositionY":496,"LeftButtonDown":false,"RightButtonDown":false,"MiddleButtonDown":false,"EventType":0,"EventTimeInTicks":637195298141671944},{"PositionX":568,"PositionY":497,"LeftButtonDown":false,"RightButtonDown":false,"MiddleButtonDown":false,"EventType":0,"EventTimeInTicks":637195298142351914},{"PositionX":564,"PositionY":498,"LeftButtonDown":false,"RightButtonDown":false,"MiddleButtonDown":false,"EventType":0,"EventTimeInTicks":637195298142511909},{"PositionX":549,"PositionY":501,"LeftButtonDown":false,"RightButtonDown":false,"MiddleButtonDown":false,"EventType":0,"EventTimeInTicks":637195298142741923},{"PositionX":535,"PositionY":504,"LeftButtonDown":false,"RightButtonDown":false,"MiddleButtonDown":false,"EventType":0,"EventTimeInTicks":637195298142821954},{"PositionX":519,"PositionY":504,"LeftButtonDown":false,"RightButtonDown":false,"MiddleButtonDown":false,"EventType":0,"EventTimeInTicks":637195298142981920},{"PositionX":503,"PositionY":504,"LeftButtonDown":false,"RightButtonDown":false,"MiddleButtonDown":false,"EventType":0,"EventTimeInTicks":637195298143141988},{"PositionX":489,"PositionY":504,"LeftButtonDown":false,"RightButtonDown":false,"MiddleButtonDown":false,"EventType":0,"EventTimeInTicks":637195298143231906},{"PositionX":483,"PositionY":503,"LeftButtonDown":false,"RightButtonDown":false,"MiddleButtonDown":false,"EventType":0,"EventTimeInTicks":637195298143381904},{"PositionX":481,"PositionY":502,"LeftButtonDown":false,"RightButtonDown":false,"MiddleButtonDown":false,"EventType":0,"EventTimeInTicks":637195298143602087},{"PositionX":480,"PositionY":502,"LeftButtonDown":false,"RightButtonDown":false,"MiddleButtonDown":false,"EventType":0,"EventTimeInTicks":637195298145971954},{"PositionX":477,"PositionY":502,"LeftButtonDown":false,"RightButtonDown":false,"MiddleButtonDown":false,"EventType":0,"EventTimeInTicks":637195298146051887},{"PositionX":473,"PositionY":502,"LeftButtonDown":false,"RightButtonDown":false,"MiddleButtonDown":false,"EventType":0,"EventTimeInTicks":637195298146252029},{"PositionX":467,"PositionY":504,"LeftButtonDown":false,"RightButtonDown":false,"MiddleButtonDown":false,"EventType":0,"EventTimeInTicks":637195298146411883},{"PositionX":459,"PositionY":505,"LeftButtonDown":false,"RightButtonDown":false,"MiddleButtonDown":false,"EventType":0,"EventTimeInTicks":637195298146551892},{"PositionX":448,"PositionY":506,"LeftButtonDown":false,"RightButtonDown":false,"MiddleButtonDown":false,"EventType":0,"EventTimeInTicks":637195298146681879},{"PositionX":432,"PositionY":507,"LeftButtonDown":false,"RightButtonDown":false,"MiddleButtonDown":false,"EventType":0,"EventTimeInTicks":637195298146841889},{"PositionX":421,"PositionY":507,"LeftButtonDown":false,"RightButtonDown":false,"MiddleButtonDown":false,"EventType":0,"EventTimeInTicks":637195298146991879},{"PositionX":413,"PositionY":507,"LeftButtonDown":false,"RightButtonDown":false,"MiddleButtonDown":false,"EventType":0,"EventTimeInTicks":637195298147141870},{"PositionX":409,"PositionY":507,"LeftButtonDown":false,"RightButtonDown":false,"MiddleButtonDown":false,"EventType":0,"EventTimeInTicks":637195298147331864},{"PositionX":409,"PositionY":506,"LeftButtonDown":false,"RightButtonDown":false,"MiddleButtonDown":false,"EventType":0,"EventTimeInTicks":637195298147531887},{"PositionX":409,"PositionY":505,"LeftButtonDown":false,"RightButtonDown":false,"MiddleButtonDown":false,"EventType":0,"EventTimeInTicks":637195298147752034},{"PositionX":409,"PositionY":504,"LeftButtonDown":false,"RightButtonDown":false,"MiddleButtonDown":false,"EventType":0,"EventTimeInTicks":637195298147842031},{"PositionX":409,"PositionY":503,"LeftButtonDown":false,"RightButtonDown":false,"MiddleButtonDown":false,"EventType":0,"EventTimeInTicks":637195298157601819},{"PositionX":407,"PositionY":501,"LeftButtonDown":false,"RightButtonDown":false,"MiddleButtonDown":false,"EventType":0,"EventTimeInTicks":637195298157771803},{"PositionX":398,"PositionY":490,"LeftButtonDown":false,"RightButtonDown":false,"MiddleButtonDown":false,"EventType":0,"EventTimeInTicks":637195298157931823},{"PositionX":387,"PositionY":473,"LeftButtonDown":false,"RightButtonDown":false,"MiddleButtonDown":false,"EventType":0,"EventTimeInTicks":637195298158171813},{"PositionX":374,"PositionY":454,"LeftButtonDown":false,"RightButtonDown":false,"MiddleButtonDown":false,"EventType":0,"EventTimeInTicks":637195298158241786},{"PositionX":357,"PositionY":433,"LeftButtonDown":false,"RightButtonDown":false,"MiddleButtonDown":false,"EventType":0,"EventTimeInTicks":637195298158391910},{"PositionX":341,"PositionY":413,"LeftButtonDown":false,"RightButtonDown":false,"MiddleButtonDown":false,"EventType":0,"EventTimeInTicks":637195298158531788},{"PositionX":331,"PositionY":396,"LeftButtonDown":false,"RightButtonDown":false,"MiddleButtonDown":false,"EventType":0,"EventTimeInTicks":637195298158681779},{"PositionX":324,"PositionY":386,"LeftButtonDown":false,"RightButtonDown":false,"MiddleButtonDown":false,"EventType":0,"EventTimeInTicks":637195298158921804},{"PositionX":320,"PositionY":378,"LeftButtonDown":false,"RightButtonDown":false,"MiddleButtonDown":false,"EventType":0,"EventTimeInTicks":637195298158981954},{"PositionX":314,"PositionY":369,"LeftButtonDown":false,"RightButtonDown":false,"MiddleButtonDown":false,"EventType":0,"EventTimeInTicks":637195298159201785},{"PositionX":310,"PositionY":357,"LeftButtonDown":false,"RightButtonDown":false,"MiddleButtonDown":false,"EventType":0,"EventTimeInTicks":637195298159351802},{"PositionX":305,"PositionY":343,"LeftButtonDown":false,"RightButtonDown":false,"MiddleButtonDown":false,"EventType":0,"EventTimeInTicks":637195298159501912},{"PositionX":298,"PositionY":331,"LeftButtonDown":false,"RightButtonDown":false,"MiddleButtonDown":false,"EventType":0,"EventTimeInTicks":637195298159641784},{"PositionX":292,"PositionY":319,"LeftButtonDown":false,"RightButtonDown":false,"MiddleButtonDown":false,"EventType":0,"EventTimeInTicks":637195298159821777},{"PositionX":286,"PositionY":308,"LeftButtonDown":false,"RightButtonDown":false,"MiddleButtonDown":false,"EventType":0,"EventTimeInTicks":637195298159971773},{"PositionX":279,"PositionY":296,"LeftButtonDown":false,"RightButtonDown":false,"MiddleButtonDown":false,"EventType":0,"EventTimeInTicks":637195298160081769},{"PositionX":274,"PositionY":288,"LeftButtonDown":false,"RightButtonDown":false,"MiddleButtonDown":false,"EventType":0,"EventTimeInTicks":637195298160291771},{"PositionX":269,"PositionY":281,"LeftButtonDown":false,"RightButtonDown":false,"MiddleButtonDown":false,"EventType":0,"EventTimeInTicks":637195298160431769},{"PositionX":264,"PositionY":274,"LeftButtonDown":false,"RightButtonDown":false,"MiddleButtonDown":false,"EventType":0,"EventTimeInTicks":637195298160591775},{"PositionX":258,"PositionY":263,"LeftButtonDown":false,"RightButtonDown":false,"MiddleButtonDown":false,"EventType":0,"EventTimeInTicks":637195298160751779},{"PositionX":252,"PositionY":255,"LeftButtonDown":false,"RightButtonDown":false,"MiddleButtonDown":false,"EventType":0,"EventTimeInTicks":637195298160921765},{"PositionX":248,"PositionY":248,"LeftButtonDown":false,"RightButtonDown":false,"MiddleButtonDown":false,"EventType":0,"EventTimeInTicks":637195298161061767},{"PositionX":244,"PositionY":243,"LeftButtonDown":false,"RightButtonDown":false,"MiddleButtonDown":false,"EventType":0,"EventTimeInTicks":637195298161191773},{"PositionX":240,"PositionY":235,"LeftButtonDown":false,"RightButtonDown":false,"MiddleButtonDown":false,"EventType":0,"EventTimeInTicks":637195298161411769},{"PositionX":234,"PositionY":224,"LeftButtonDown":false,"RightButtonDown":false,"MiddleButtonDown":false,"EventType":0,"EventTimeInTicks":637195298161521766},{"PositionX":228,"PositionY":211,"LeftButtonDown":false,"RightButtonDown":false,"MiddleButtonDown":false,"EventType":0,"EventTimeInTicks":637195298161671795},{"PositionX":222,"PositionY":199,"LeftButtonDown":false,"RightButtonDown":false,"MiddleButtonDown":false,"EventType":0,"EventTimeInTicks":637195298161831780},{"PositionX":217,"PositionY":189,"LeftButtonDown":false,"RightButtonDown":false,"MiddleButtonDown":false,"EventType":0,"EventTimeInTicks":637195298161971783},{"PositionX":214,"PositionY":182,"LeftButtonDown":false,"RightButtonDown":false,"MiddleButtonDown":false,"EventType":0,"EventTimeInTicks":637195298162111796},{"PositionX":212,"PositionY":173,"LeftButtonDown":false,"RightButtonDown":false,"MiddleButtonDown":false,"EventType":0,"EventTimeInTicks":637195298162331772},{"PositionX":211,"PositionY":165,"LeftButtonDown":false,"RightButtonDown":false,"MiddleButtonDown":false,"EventType":0,"EventTimeInTicks":637195298162461759},{"PositionX":209,"PositionY":155,"LeftButtonDown":false,"RightButtonDown":false,"MiddleButtonDown":false,"EventType":0,"EventTimeInTicks":637195298162621777},{"PositionX":207,"PositionY":146,"LeftButtonDown":false,"RightButtonDown":false,"MiddleButtonDown":false,"EventType":0,"EventTimeInTicks":637195298162771892},{"PositionX":205,"PositionY":135,"LeftButtonDown":false,"RightButtonDown":false,"MiddleButtonDown":false,"EventType":0,"EventTimeInTicks":637195298162941757},{"PositionX":203,"PositionY":124,"LeftButtonDown":false,"RightButtonDown":false,"MiddleButtonDown":false,"EventType":0,"EventTimeInTicks":637195298163111763},{"PositionX":202,"PositionY":114,"LeftButtonDown":false,"RightButtonDown":false,"MiddleButtonDown":false,"EventType":0,"EventTimeInTicks":637195298163271747},{"PositionX":202,"PositionY":106,"LeftButtonDown":false,"RightButtonDown":false,"MiddleButtonDown":false,"EventType":0,"EventTimeInTicks":637195298163421773},{"PositionX":203,"PositionY":99,"LeftButtonDown":false,"RightButtonDown":false,"MiddleButtonDown":false,"EventType":0,"EventTimeInTicks":637195298163581769},{"PositionX":204,"PositionY":94,"LeftButtonDown":false,"RightButtonDown":false,"MiddleButtonDown":false,"EventType":0,"EventTimeInTicks":637195298163721749},{"PositionX":206,"PositionY":89,"LeftButtonDown":false,"RightButtonDown":false,"MiddleButtonDown":false,"EventType":0,"EventTimeInTicks":637195298163911757},{"PositionX":208,"PositionY":80,"LeftButtonDown":false,"RightButtonDown":false,"MiddleButtonDown":false,"EventType":0,"EventTimeInTicks":637195298164071769},{"PositionX":209,"PositionY":78,"LeftButtonDown":false,"RightButtonDown":false,"MiddleButtonDown":false,"EventType":0,"EventTimeInTicks":637195298164141756},{"PositionX":211,"PositionY":71,"LeftButtonDown":false,"RightButtonDown":false,"MiddleButtonDown":false,"EventType":0,"EventTimeInTicks":637195298164361749},{"PositionX":213,"PositionY":65,"LeftButtonDown":false,"RightButtonDown":false,"MiddleButtonDown":false,"EventType":0,"EventTimeInTicks":637195298164521769},{"PositionX":216,"PositionY":57,"LeftButtonDown":false,"RightButtonDown":false,"MiddleButtonDown":false,"EventType":0,"EventTimeInTicks":637195298164741749},{"PositionX":217,"PositionY":55,"LeftButtonDown":false,"RightButtonDown":false,"MiddleButtonDown":false,"EventType":0,"EventTimeInTicks":637195298164831737},{"PositionX":219,"PositionY":51,"LeftButtonDown":false,"RightButtonDown":false,"MiddleButtonDown":false,"EventType":0,"EventTimeInTicks":637195298164981743},{"PositionX":221,"PositionY":46,"LeftButtonDown":false,"RightButtonDown":false,"MiddleButtonDown":false,"EventType":0,"EventTimeInTicks":637195298165161730},{"PositionX":223,"PositionY":41,"LeftButtonDown":false,"RightButtonDown":false,"MiddleButtonDown":false,"EventType":0,"EventTimeInTicks":637195298165301742},{"PositionX":227,"PositionY":32,"LeftButtonDown":false,"RightButtonDown":false,"MiddleButtonDown":false,"EventType":0,"EventTimeInTicks":637195298165501737},{"PositionX":227,"PositionY":29,"LeftButtonDown":false,"RightButtonDown":false,"MiddleButtonDown":false,"EventType":0,"EventTimeInTicks":637195298165581728},{"PositionX":228,"PositionY":26,"LeftButtonDown":false,"RightButtonDown":false,"MiddleButtonDown":false,"EventType":0,"EventTimeInTicks":637195298165721763},{"PositionX":228,"PositionY":23,"LeftButtonDown":false,"RightButtonDown":false,"MiddleButtonDown":false,"EventType":0,"EventTimeInTicks":637195298166191733},{"PositionX":228,"PositionY":21,"LeftButtonDown":false,"RightButtonDown":false,"MiddleButtonDown":false,"EventType":0,"EventTimeInTicks":637195298166431769},{"PositionX":227,"PositionY":21,"LeftButtonDown":false,"RightButtonDown":false,"MiddleButtonDown":false,"EventType":0,"EventTimeInTicks":637195298167571761},{"PositionX":227,"PositionY":20,"LeftButtonDown":false,"RightButtonDown":false,"MiddleButtonDown":false,"EventType":0,"EventTimeInTicks":637195298168471724},{"PositionX":226,"PositionY":20,"LeftButtonDown":false,"RightButtonDown":false,"MiddleButtonDown":false,"EventType":0,"EventTimeInTicks":637195298168651736},{"PositionX":225,"PositionY":20,"LeftButtonDown":false,"RightButtonDown":false,"MiddleButtonDown":false,"EventType":0,"EventTimeInTicks":637195298169001730},{"PositionX":224,"PositionY":19,"LeftButtonDown":false,"RightButtonDown":false,"MiddleButtonDown":false,"EventType":0,"EventTimeInTicks":637195298169261851},{"PositionX":226,"PositionY":20,"LeftButtonDown":false,"RightButtonDown":false,"MiddleButtonDown":false,"EventType":0,"EventTimeInTicks":637195298185131672},{"PositionX":238,"PositionY":27,"LeftButtonDown":false,"RightButtonDown":false,"MiddleButtonDown":false,"EventType":0,"EventTimeInTicks":637195298185301620},{"PositionX":254,"PositionY":30,"LeftButtonDown":false,"RightButtonDown":false,"MiddleButtonDown":false,"EventType":0,"EventTimeInTicks":637195298185471608},{"PositionX":273,"PositionY":30,"LeftButtonDown":false,"RightButtonDown":false,"MiddleButtonDown":false,"EventType":0,"EventTimeInTicks":637195298185641652},{"PositionX":297,"PositionY":28,"LeftButtonDown":false,"RightButtonDown":false,"MiddleButtonDown":false,"EventType":0,"EventTimeInTicks":637195298185811608},{"PositionX":341,"PositionY":30,"LeftButtonDown":false,"RightButtonDown":false,"MiddleButtonDown":false,"EventType":0,"EventTimeInTicks":637195298185981627},{"PositionX":381,"PositionY":33,"LeftButtonDown":false,"RightButtonDown":false,"MiddleButtonDown":false,"EventType":0,"EventTimeInTicks":637195298186061654},{"PositionX":414,"PositionY":32,"LeftButtonDown":false,"RightButtonDown":false,"MiddleButtonDown":false,"EventType":0,"EventTimeInTicks":637195298186241589},{"PositionX":451,"PositionY":31,"LeftButtonDown":false,"RightButtonDown":false,"MiddleButtonDown":false,"EventType":0,"EventTimeInTicks":637195298186411618},{"PositionX":479,"PositionY":31,"LeftButtonDown":false,"RightButtonDown":false,"MiddleButtonDown":false,"EventType":0,"EventTimeInTicks":637195298186581617},{"PositionX":503,"PositionY":33,"LeftButtonDown":false,"RightButtonDown":false,"MiddleButtonDown":false,"EventType":0,"EventTimeInTicks":637195298186751581},{"PositionX":518,"PositionY":34,"LeftButtonDown":false,"RightButtonDown":false,"MiddleButtonDown":false,"EventType":0,"EventTimeInTicks":637195298186921597},{"PositionX":526,"PositionY":34,"LeftButtonDown":false,"RightButtonDown":false,"MiddleButtonDown":false,"EventType":0,"EventTimeInTicks":637195298187001634},{"PositionX":530,"PositionY":34,"LeftButtonDown":false,"RightButtonDown":false,"MiddleButtonDown":false,"EventType":0,"EventTimeInTicks":637195298187191599},{"PositionX":531,"PositionY":33,"LeftButtonDown":false,"RightButtonDown":false,"MiddleButtonDown":false,"EventType":0,"EventTimeInTicks":637195298188251571},{"PositionX":522,"PositionY":30,"LeftButtonDown":false,"RightButtonDown":false,"MiddleButtonDown":false,"EventType":0,"EventTimeInTicks":637195298188451617},{"PositionX":515,"PositionY":27,"LeftButtonDown":false,"RightButtonDown":false,"MiddleButtonDown":false,"EventType":0,"EventTimeInTicks":637195298188701590},{"PositionX":505,"PositionY":26,"LeftButtonDown":false,"RightButtonDown":false,"MiddleButtonDown":false,"EventType":0,"EventTimeInTicks":637195298188831565},{"PositionX":496,"PositionY":24,"LeftButtonDown":false,"RightButtonDown":false,"MiddleButtonDown":false,"EventType":0,"EventTimeInTicks":637195298188941573},{"PositionX":485,"PositionY":22,"LeftButtonDown":false,"RightButtonDown":false,"MiddleButtonDown":false,"EventType":0,"EventTimeInTicks":637195298189071570},{"PositionX":476,"PositionY":20,"LeftButtonDown":false,"RightButtonDown":false,"MiddleButtonDown":false,"EventType":0,"EventTimeInTicks":637195298189211581},{"PositionX":471,"PositionY":19,"LeftButtonDown":false,"RightButtonDown":false,"MiddleButtonDown":false,"EventType":0,"EventTimeInTicks":637195298189361669},{"PositionX":469,"PositionY":17,"LeftButtonDown":false,"RightButtonDown":false,"MiddleButtonDown":false,"EventType":0,"EventTimeInTicks":637195298189501609},{"PositionX":468,"PositionY":17,"LeftButtonDown":false,"RightButtonDown":false,"MiddleButtonDown":false,"EventType":0,"EventTimeInTicks":637195298190311690},{"PositionX":466,"PositionY":16,"LeftButtonDown":false,"RightButtonDown":false,"MiddleButtonDown":false,"EventType":0,"EventTimeInTicks":637195298190461570},{"PositionX":465,"PositionY":15,"LeftButtonDown":false,"RightButtonDown":false,"MiddleButtonDown":false,"EventType":0,"EventTimeInTicks":637195298190621559},{"PositionX":464,"PositionY":15,"LeftButtonDown":true,"RightButtonDown":false,"MiddleButtonDown":false,"EventType":0,"EventTimeInTicks":637195298191091591},{"PositionX":465,"PositionY":15,"LeftButtonDown":false,"RightButtonDown":false,"MiddleButtonDown":false,"EventType":0,"EventTimeInTicks":637195298194691529},{"PositionX":466,"PositionY":16,"LeftButtonDown":false,"RightButtonDown":false,"MiddleButtonDown":false,"EventType":0,"EventTimeInTicks":637195298194891549},{"PositionX":467,"PositionY":18,"LeftButtonDown":false,"RightButtonDown":false,"MiddleButtonDown":false,"EventType":0,"EventTimeInTicks":637195298195681516},{"PositionX":468,"PositionY":18,"LeftButtonDown":false,"RightButtonDown":false,"MiddleButtonDown":false,"EventType":0,"EventTimeInTicks":637195298195841505},{"PositionX":469,"PositionY":19,"LeftButtonDown":false,"RightButtonDown":false,"MiddleButtonDown":false,"EventType":0,"EventTimeInTicks":637195298196061514},{"PositionX":472,"PositionY":19,"LeftButtonDown":false,"RightButtonDown":false,"MiddleButtonDown":false,"EventType":0,"EventTimeInTicks":637195298199051507},{"PositionX":481,"PositionY":21,"LeftButtonDown":false,"RightButtonDown":false,"MiddleButtonDown":false,"EventType":0,"EventTimeInTicks":637195298199251598},{"PositionX":493,"PositionY":23,"LeftButtonDown":false,"RightButtonDown":false,"MiddleButtonDown":false,"EventType":0,"EventTimeInTicks":637195298199361503},{"PositionX":512,"PositionY":25,"LeftButtonDown":false,"RightButtonDown":false,"MiddleButtonDown":false,"EventType":0,"EventTimeInTicks":637195298199531518},{"PositionX":532,"PositionY":27,"LeftButtonDown":false,"RightButtonDown":false,"MiddleButtonDown":false,"EventType":0,"EventTimeInTicks":637195298199711493},{"PositionX":550,"PositionY":29,"LeftButtonDown":false,"RightButtonDown":false,"MiddleButtonDown":false,"EventType":0,"EventTimeInTicks":637195298199801514},{"PositionX":560,"PositionY":29,"LeftButtonDown":false,"RightButtonDown":false,"MiddleButtonDown":false,"EventType":0,"EventTimeInTicks":637195298200031513},{"PositionX":565,"PositionY":29,"LeftButtonDown":false,"RightButtonDown":false,"MiddleButtonDown":false,"EventType":0,"EventTimeInTicks":637195298200141499},{"PositionX":568,"PositionY":29,"LeftButtonDown":false,"RightButtonDown":false,"MiddleButtonDown":false,"EventType":0,"EventTimeInTicks":637195298200351486},{"PositionX":574,"PositionY":29,"LeftButtonDown":false,"RightButtonDown":false,"MiddleButtonDown":false,"EventType":0,"EventTimeInTicks":637195298200451534},{"PositionX":581,"PositionY":28,"LeftButtonDown":false,"RightButtonDown":false,"MiddleButtonDown":false,"EventType":0,"EventTimeInTicks":637195298200651470},{"PositionX":587,"PositionY":27,"LeftButtonDown":false,"RightButtonDown":false,"MiddleButtonDown":false,"EventType":0,"EventTimeInTicks":637195298200831671},{"PositionX":590,"PositionY":27,"LeftButtonDown":false,"RightButtonDown":false,"MiddleButtonDown":false,"EventType":0,"EventTimeInTicks":637195298200941480},{"PositionX":592,"PositionY":26,"LeftButtonDown":false,"RightButtonDown":false,"MiddleButtonDown":false,"EventType":0,"EventTimeInTicks":637195298201131473},{"PositionX":594,"PositionY":26,"LeftButtonDown":false,"RightButtonDown":false,"MiddleButtonDown":false,"EventType":0,"EventTimeInTicks":637195298201271498},{"PositionX":599,"PositionY":26,"LeftButtonDown":false,"RightButtonDown":false,"MiddleButtonDown":false,"EventType":0,"EventTimeInTicks":637195298201451666},{"PositionX":603,"PositionY":26,"LeftButtonDown":false,"RightButtonDown":false,"MiddleButtonDown":false,"EventType":0,"EventTimeInTicks":637195298201571600},{"PositionX":606,"PositionY":26,"LeftButtonDown":false,"RightButtonDown":false,"MiddleButtonDown":false,"EventType":0,"EventTimeInTicks":637195298201751467},{"PositionX":608,"PositionY":26,"LeftButtonDown":false,"RightButtonDown":false,"MiddleButtonDown":false,"EventType":0,"EventTimeInTicks":637195298201841474},{"PositionX":612,"PositionY":26,"LeftButtonDown":false,"RightButtonDown":false,"MiddleButtonDown":false,"EventType":0,"EventTimeInTicks":637195298202001472},{"PositionX":615,"PositionY":26,"LeftButtonDown":false,"RightButtonDown":false,"MiddleButtonDown":false,"EventType":0,"EventTimeInTicks":637195298202191503},{"PositionX":618,"PositionY":26,"LeftButtonDown":false,"RightButtonDown":false,"MiddleButtonDown":false,"EventType":0,"EventTimeInTicks":637195298202281485},{"PositionX":620,"PositionY":25,"LeftButtonDown":false,"RightButtonDown":false,"MiddleButtonDown":false,"EventType":0,"EventTimeInTicks":637195298202461469},{"PositionX":622,"PositionY":25,"LeftButtonDown":false,"RightButtonDown":false,"MiddleButtonDown":false,"EventType":0,"EventTimeInTicks":637195298202741549},{"PositionX":623,"PositionY":25,"LeftButtonDown":false,"RightButtonDown":false,"MiddleButtonDown":false,"EventType":0,"EventTimeInTicks":637195298202841501},{"PositionX":621,"PositionY":25,"LeftButtonDown":false,"RightButtonDown":false,"MiddleButtonDown":false,"EventType":0,"EventTimeInTicks":637195298206901448},{"PositionX":619,"PositionY":24,"LeftButtonDown":false,"RightButtonDown":false,"MiddleButtonDown":false,"EventType":0,"EventTimeInTicks":637195298206991448},{"PositionX":615,"PositionY":24,"LeftButtonDown":false,"RightButtonDown":false,"MiddleButtonDown":false,"EventType":0,"EventTimeInTicks":637195298207171462},{"PositionX":613,"PositionY":24,"LeftButtonDown":false,"RightButtonDown":false,"MiddleButtonDown":false,"EventType":0,"EventTimeInTicks":637195298207341451},{"PositionX":610,"PositionY":24,"LeftButtonDown":false,"RightButtonDown":false,"MiddleButtonDown":false,"EventType":0,"EventTimeInTicks":637195298207451467},{"PositionX":607,"PositionY":24,"LeftButtonDown":false,"RightButtonDown":false,"MiddleButtonDown":false,"EventType":0,"EventTimeInTicks":637195298207641494},{"PositionX":604,"PositionY":24,"LeftButtonDown":false,"RightButtonDown":false,"MiddleButtonDown":false,"EventType":0,"EventTimeInTicks":637195298207851594},{"PositionX":601,"PositionY":23,"LeftButtonDown":false,"RightButtonDown":false,"MiddleButtonDown":false,"EventType":0,"EventTimeInTicks":637195298207951431},{"PositionX":597,"PositionY":22,"LeftButtonDown":false,"RightButtonDown":false,"MiddleButtonDown":false,"EventType":0,"EventTimeInTicks":637195298208141446},{"PositionX":591,"PositionY":21,"LeftButtonDown":false,"RightButtonDown":false,"MiddleButtonDown":false,"EventType":0,"EventTimeInTicks":637195298208221450},{"PositionX":584,"PositionY":19,"LeftButtonDown":false,"RightButtonDown":false,"MiddleButtonDown":false,"EventType":0,"EventTimeInTicks":637195298208401447},{"PositionX":578,"PositionY":18,"LeftButtonDown":false,"RightButtonDown":false,"MiddleButtonDown":false,"EventType":0,"EventTimeInTicks":637195298208581439},{"PositionX":574,"PositionY":17,"LeftButtonDown":false,"RightButtonDown":false,"MiddleButtonDown":false,"EventType":0,"EventTimeInTicks":637195298208771434},{"PositionX":573,"PositionY":17,"LeftButtonDown":false,"RightButtonDown":false,"MiddleButtonDown":false,"EventType":0,"EventTimeInTicks":637195298208951418},{"PositionX":572,"PositionY":17,"LeftButtonDown":false,"RightButtonDown":false,"MiddleButtonDown":false,"EventType":0,"EventTimeInTicks":637195298209651441},{"PositionX":571,"PositionY":17,"LeftButtonDown":false,"RightButtonDown":false,"MiddleButtonDown":false,"EventType":0,"EventTimeInTicks":637195298214171418},{"PositionX":569,"PositionY":17,"LeftButtonDown":false,"RightButtonDown":false,"MiddleButtonDown":false,"EventType":0,"EventTimeInTicks":637195298214371441},{"PositionX":568,"PositionY":18,"LeftButtonDown":false,"RightButtonDown":false,"MiddleButtonDown":false,"EventType":0,"EventTimeInTicks":637195298214461441},{"PositionX":565,"PositionY":19,"LeftButtonDown":false,"RightButtonDown":false,"MiddleButtonDown":false,"EventType":0,"EventTimeInTicks":637195298214651414},{"PositionX":564,"PositionY":20,"LeftButtonDown":false,"RightButtonDown":false,"MiddleButtonDown":false,"EventType":0,"EventTimeInTicks":637195298214851416},{"PositionX":563,"PositionY":21,"LeftButtonDown":false,"RightButtonDown":false,"MiddleButtonDown":false,"EventType":0,"EventTimeInTicks":637195298214981402},{"PositionX":562,"PositionY":21,"LeftButtonDown":false,"RightButtonDown":false,"MiddleButtonDown":false,"EventType":0,"EventTimeInTicks":637195298216281431},{"PositionX":561,"PositionY":21,"LeftButtonDown":false,"RightButtonDown":false,"MiddleButtonDown":false,"EventType":0,"EventTimeInTicks":637195298216361420},{"PositionX":552,"PositionY":21,"LeftButtonDown":false,"RightButtonDown":false,"MiddleButtonDown":false,"EventType":0,"EventTimeInTicks":637195298216591372},{"PositionX":544,"PositionY":20,"LeftButtonDown":false,"RightButtonDown":false,"MiddleButtonDown":false,"EventType":0,"EventTimeInTicks":637195298216681399},{"PositionX":538,"PositionY":17,"LeftButtonDown":false,"RightButtonDown":false,"MiddleButtonDown":false,"EventType":0,"EventTimeInTicks":637195298216801395},{"PositionX":535,"PositionY":17,"LeftButtonDown":false,"RightButtonDown":false,"MiddleButtonDown":false,"EventType":0,"EventTimeInTicks":637195298216991369},{"PositionX":533,"PositionY":17,"LeftButtonDown":false,"RightButtonDown":false,"MiddleButtonDown":false,"EventType":0,"EventTimeInTicks":637195298217511373},{"PositionX":522,"PositionY":18,"LeftButtonDown":false,"RightButtonDown":false,"MiddleButtonDown":false,"EventType":0,"EventTimeInTicks":637195298217601372},{"PositionX":508,"PositionY":20,"LeftButtonDown":false,"RightButtonDown":false,"MiddleButtonDown":false,"EventType":0,"EventTimeInTicks":637195298217831400},{"PositionX":496,"PositionY":21,"LeftButtonDown":false,"RightButtonDown":false,"MiddleButtonDown":false,"EventType":0,"EventTimeInTicks":637195298217931381},{"PositionX":485,"PositionY":23,"LeftButtonDown":false,"RightButtonDown":false,"MiddleButtonDown":false,"EventType":0,"EventTimeInTicks":637195298218111404},{"PositionX":476,"PositionY":25,"LeftButtonDown":false,"RightButtonDown":false,"MiddleButtonDown":false,"EventType":0,"EventTimeInTicks":637195298218291355},{"PositionX":469,"PositionY":28,"LeftButtonDown":false,"RightButtonDown":false,"MiddleButtonDown":false,"EventType":0,"EventTimeInTicks":637195298218381357},{"PositionX":464,"PositionY":30,"LeftButtonDown":false,"RightButtonDown":false,"MiddleButtonDown":false,"EventType":0,"EventTimeInTicks":637195298218551407},{"PositionX":458,"PositionY":34,"LeftButtonDown":false,"RightButtonDown":false,"MiddleButtonDown":false,"EventType":0,"EventTimeInTicks":637195298218751378},{"PositionX":452,"PositionY":35,"LeftButtonDown":false,"RightButtonDown":false,"MiddleButtonDown":false,"EventType":0,"EventTimeInTicks":637195298218921464},{"PositionX":448,"PositionY":37,"LeftButtonDown":false,"RightButtonDown":false,"MiddleButtonDown":false,"EventType":0,"EventTimeInTicks":637195298219051382},{"PositionX":443,"PositionY":38,"LeftButtonDown":false,"RightButtonDown":false,"MiddleButtonDown":false,"EventType":0,"EventTimeInTicks":637195298219141366},{"PositionX":441,"PositionY":39,"LeftButtonDown":false,"RightButtonDown":false,"MiddleButtonDown":false,"EventType":0,"EventTimeInTicks":637195298219391405},{"PositionX":444,"PositionY":39,"LeftButtonDown":false,"RightButtonDown":false,"MiddleButtonDown":false,"EventType":0,"EventTimeInTicks":637195298224971317},{"PositionX":458,"PositionY":38,"LeftButtonDown":false,"RightButtonDown":false,"MiddleButtonDown":false,"EventType":0,"EventTimeInTicks":637195298225141315},{"PositionX":488,"PositionY":34,"LeftButtonDown":false,"RightButtonDown":false,"MiddleButtonDown":false,"EventType":0,"EventTimeInTicks":637195298225401309},{"PositionX":515,"PositionY":32,"LeftButtonDown":false,"RightButtonDown":false,"MiddleButtonDown":false,"EventType":0,"EventTimeInTicks":637195298225551313},{"PositionX":556,"PositionY":33,"LeftButtonDown":false,"RightButtonDown":false,"MiddleButtonDown":false,"EventType":0,"EventTimeInTicks":637195298225711312},{"PositionX":612,"PositionY":36,"LeftButtonDown":false,"RightButtonDown":false,"MiddleButtonDown":false,"EventType":0,"EventTimeInTicks":637195298225931318},{"PositionX":662,"PositionY":40,"LeftButtonDown":false,"RightButtonDown":false,"MiddleButtonDown":false,"EventType":0,"EventTimeInTicks":637195298226081293},{"PositionX":697,"PositionY":43,"LeftButtonDown":false,"RightButtonDown":false,"MiddleButtonDown":false,"EventType":0,"EventTimeInTicks":637195298226201319},{"PositionX":717,"PositionY":44,"LeftButtonDown":false,"RightButtonDown":false,"MiddleButtonDown":false,"EventType":0,"EventTimeInTicks":637195298226361289},{"PositionX":729,"PositionY":46,"LeftButtonDown":false,"RightButtonDown":false,"MiddleButtonDown":false,"EventType":0,"EventTimeInTicks":637195298226541275},{"PositionX":735,"PositionY":46,"LeftButtonDown":false,"RightButtonDown":false,"MiddleButtonDown":false,"EventType":0,"EventTimeInTicks":637195298226711287},{"PositionX":734,"PositionY":46,"LeftButtonDown":false,"RightButtonDown":false,"MiddleButtonDown":false,"EventType":0,"EventTimeInTicks":637195298229131331},{"PositionX":734,"PositionY":45,"LeftButtonDown":false,"RightButtonDown":false,"MiddleButtonDown":false,"EventType":0,"EventTimeInTicks":637195298229611439},{"PositionX":735,"PositionY":44,"LeftButtonDown":false,"RightButtonDown":false,"MiddleButtonDown":false,"EventType":0,"EventTimeInTicks":637195298229761281},{"PositionX":737,"PositionY":43,"LeftButtonDown":false,"RightButtonDown":false,"MiddleButtonDown":false,"EventType":0,"EventTimeInTicks":637195298229991352},{"PositionX":743,"PositionY":41,"LeftButtonDown":false,"RightButtonDown":false,"MiddleButtonDown":false,"EventType":0,"EventTimeInTicks":637195298230171278},{"PositionX":745,"PositionY":40,"LeftButtonDown":false,"RightButtonDown":false,"MiddleButtonDown":false,"EventType":0,"EventTimeInTicks":637195298230431277},{"PositionX":745,"PositionY":39,"LeftButtonDown":false,"RightButtonDown":false,"MiddleButtonDown":false,"EventType":0,"EventTimeInTicks":637195298230521281},{"PositionX":745,"PositionY":38,"LeftButtonDown":false,"RightButtonDown":false,"MiddleButtonDown":false,"EventType":0,"EventTimeInTicks":637195298231751260},{"PositionX":742,"PositionY":38,"LeftButtonDown":false,"RightButtonDown":false,"MiddleButtonDown":false,"EventType":0,"EventTimeInTicks":637195298232191265},{"PositionX":741,"PositionY":38,"LeftButtonDown":false,"RightButtonDown":false,"MiddleButtonDown":false,"EventType":0,"EventTimeInTicks":637195298232281377},{"PositionX":739,"PositionY":38,"LeftButtonDown":false,"RightButtonDown":false,"MiddleButtonDown":false,"EventType":0,"EventTimeInTicks":637195298232471256},{"PositionX":736,"PositionY":39,"LeftButtonDown":false,"RightButtonDown":false,"MiddleButtonDown":false,"EventType":0,"EventTimeInTicks":637195298232651380},{"PositionX":732,"PositionY":40,"LeftButtonDown":false,"RightButtonDown":false,"MiddleButtonDown":false,"EventType":0,"EventTimeInTicks":637195298232801266},{"PositionX":729,"PositionY":40,"LeftButtonDown":false,"RightButtonDown":false,"MiddleButtonDown":false,"EventType":0,"EventTimeInTicks":637195298232891252},{"PositionX":723,"PositionY":40,"LeftButtonDown":false,"RightButtonDown":false,"MiddleButtonDown":false,"EventType":0,"EventTimeInTicks":637195298233061255},{"PositionX":712,"PositionY":41,"LeftButtonDown":false,"RightButtonDown":false,"MiddleButtonDown":false,"EventType":0,"EventTimeInTicks":637195298233301283},{"PositionX":700,"PositionY":41,"LeftButtonDown":false,"RightButtonDown":false,"MiddleButtonDown":false,"EventType":0,"EventTimeInTicks":637195298233461281},{"PositionX":688,"PositionY":41,"LeftButtonDown":false,"RightButtonDown":false,"MiddleButtonDown":false,"EventType":0,"EventTimeInTicks":637195298233611236},{"PositionX":677,"PositionY":41,"LeftButtonDown":false,"RightButtonDown":false,"MiddleButtonDown":false,"EventType":0,"EventTimeInTicks":637195298233801256},{"PositionX":671,"PositionY":40,"LeftButtonDown":false,"RightButtonDown":false,"MiddleButtonDown":false,"EventType":0,"EventTimeInTicks":637195298233881258},{"PositionX":667,"PositionY":40,"LeftButtonDown":false,"RightButtonDown":false,"MiddleButtonDown":false,"EventType":0,"EventTimeInTicks":637195298234051341},{"PositionX":665,"PositionY":39,"LeftButtonDown":false,"RightButtonDown":false,"MiddleButtonDown":false,"EventType":0,"EventTimeInTicks":637195298234231275},{"PositionX":661,"PositionY":39,"LeftButtonDown":false,"RightButtonDown":false,"MiddleButtonDown":false,"EventType":0,"EventTimeInTicks":637195298234511243},{"PositionX":659,"PositionY":39,"LeftButtonDown":false,"RightButtonDown":false,"MiddleButtonDown":false,"EventType":0,"EventTimeInTicks":637195298234601314},{"PositionX":646,"PositionY":39,"LeftButtonDown":false,"RightButtonDown":false,"MiddleButtonDown":false,"EventType":0,"EventTimeInTicks":637195298234901370},{"PositionX":644,"PositionY":40,"LeftButtonDown":false,"RightButtonDown":false,"MiddleButtonDown":false,"EventType":0,"EventTimeInTicks":637195298234981358},{"PositionX":638,"PositionY":41,"LeftButtonDown":false,"RightButtonDown":false,"MiddleButtonDown":false,"EventType":0,"EventTimeInTicks":637195298235141236},{"PositionX":629,"PositionY":43,"LeftButtonDown":false,"RightButtonDown":false,"MiddleButtonDown":false,"EventType":0,"EventTimeInTicks":637195298235311365},{"PositionX":620,"PositionY":47,"LeftButtonDown":false,"RightButtonDown":false,"MiddleButtonDown":false,"EventType":0,"EventTimeInTicks":637195298235491243},{"PositionX":608,"PositionY":54,"LeftButtonDown":false,"RightButtonDown":false,"MiddleButtonDown":false,"EventType":0,"EventTimeInTicks":637195298235621248},{"PositionX":595,"PositionY":63,"LeftButtonDown":false,"RightButtonDown":false,"MiddleButtonDown":false,"EventType":0,"EventTimeInTicks":637195298235781241},{"PositionX":578,"PositionY":71,"LeftButtonDown":false,"RightButtonDown":false,"MiddleButtonDown":false,"EventType":0,"EventTimeInTicks":637195298235921236},{"PositionX":564,"PositionY":78,"LeftButtonDown":false,"RightButtonDown":false,"MiddleButtonDown":false,"EventType":0,"EventTimeInTicks":637195298236111253},{"PositionX":549,"PositionY":84,"LeftButtonDown":false,"RightButtonDown":false,"MiddleButtonDown":false,"EventType":0,"EventTimeInTicks":637195298236281235},{"PositionX":507,"PositionY":108,"LeftButtonDown":false,"RightButtonDown":false,"MiddleButtonDown":false,"EventType":0,"EventTimeInTicks":637195298236681232},{"PositionX":462,"PositionY":141,"LeftButtonDown":false,"RightButtonDown":false,"MiddleButtonDown":false,"EventType":0,"EventTimeInTicks":637195298236921282},{"PositionX":429,"PositionY":163,"LeftButtonDown":false,"RightButtonDown":false,"MiddleButtonDown":false,"EventType":0,"EventTimeInTicks":637195298237111234},{"PositionX":398,"PositionY":184,"LeftButtonDown":false,"RightButtonDown":false,"MiddleButtonDown":false,"EventType":0,"EventTimeInTicks":637195298237201249},{"PositionX":384,"PositionY":196,"LeftButtonDown":false,"RightButtonDown":false,"MiddleButtonDown":false,"EventType":0,"EventTimeInTicks":637195298237391334},{"PositionX":372,"PositionY":209,"LeftButtonDown":false,"RightButtonDown":false,"MiddleButtonDown":false,"EventType":0,"EventTimeInTicks":637195298237581213},{"PositionX":363,"PositionY":218,"LeftButtonDown":false,"RightButtonDown":false,"MiddleButtonDown":false,"EventType":0,"EventTimeInTicks":637195298237681234},{"PositionX":355,"PositionY":232,"LeftButtonDown":false,"RightButtonDown":false,"MiddleButtonDown":false,"EventType":0,"EventTimeInTicks":637195298237851218},{"PositionX":347,"PositionY":250,"LeftButtonDown":false,"RightButtonDown":false,"MiddleButtonDown":false,"EventType":0,"EventTimeInTicks":637195298237941246},{"PositionX":337,"PositionY":287,"LeftButtonDown":false,"RightButtonDown":false,"MiddleButtonDown":false,"EventType":0,"EventTimeInTicks":637195298238121360},{"PositionX":325,"PositionY":323,"LeftButtonDown":false,"RightButtonDown":false,"MiddleButtonDown":false,"EventType":0,"EventTimeInTicks":637195298238281194},{"PositionX":319,"PositionY":347,"LeftButtonDown":false,"RightButtonDown":false,"MiddleButtonDown":false,"EventType":0,"EventTimeInTicks":637195298238501190},{"PositionX":313,"PositionY":361,"LeftButtonDown":false,"RightButtonDown":false,"MiddleButtonDown":false,"EventType":0,"EventTimeInTicks":637195298238581311},{"PositionX":307,"PositionY":368,"LeftButtonDown":false,"RightButtonDown":false,"MiddleButtonDown":false,"EventType":0,"EventTimeInTicks":637195298238721227},{"PositionX":304,"PositionY":374,"LeftButtonDown":false,"RightButtonDown":false,"MiddleButtonDown":false,"EventType":0,"EventTimeInTicks":637195298238901216},{"PositionX":299,"PositionY":380,"LeftButtonDown":false,"RightButtonDown":false,"MiddleButtonDown":false,"EventType":0,"EventTimeInTicks":637195298239061215},{"PositionX":294,"PositionY":385,"LeftButtonDown":false,"RightButtonDown":false,"MiddleButtonDown":false,"EventType":0,"EventTimeInTicks":637195298239231343},{"PositionX":287,"PositionY":391,"LeftButtonDown":false,"RightButtonDown":false,"MiddleButtonDown":false,"EventType":0,"EventTimeInTicks":637195298239411200},{"PositionX":277,"PositionY":399,"LeftButtonDown":false,"RightButtonDown":false,"MiddleButtonDown":false,"EventType":0,"EventTimeInTicks":637195298239501228},{"PositionX":265,"PositionY":407,"LeftButtonDown":false,"RightButtonDown":false,"MiddleButtonDown":false,"EventType":0,"EventTimeInTicks":637195298239671213},{"PositionX":247,"PositionY":417,"LeftButtonDown":false,"RightButtonDown":false,"MiddleButtonDown":false,"EventType":0,"EventTimeInTicks":637195298239851201},{"PositionX":229,"PositionY":431,"LeftButtonDown":false,"RightButtonDown":false,"MiddleButtonDown":false,"EventType":0,"EventTimeInTicks":637195298240031335},{"PositionX":213,"PositionY":445,"LeftButtonDown":false,"RightButtonDown":false,"MiddleButtonDown":false,"EventType":0,"EventTimeInTicks":637195298240191245},{"PositionX":200,"PositionY":455,"LeftButtonDown":false,"RightButtonDown":false,"MiddleButtonDown":false,"EventType":0,"EventTimeInTicks":637195298240351229},{"PositionX":189,"PositionY":466,"LeftButtonDown":false,"RightButtonDown":false,"MiddleButtonDown":false,"EventType":0,"EventTimeInTicks":637195298240521192},{"PositionX":182,"PositionY":478,"LeftButtonDown":false,"RightButtonDown":false,"MiddleButtonDown":false,"EventType":0,"EventTimeInTicks":637195298240601199},{"PositionX":175,"PositionY":493,"LeftButtonDown":false,"RightButtonDown":false,"MiddleButtonDown":false,"EventType":0,"EventTimeInTicks":637195298240771318},{"PositionX":169,"PositionY":506,"LeftButtonDown":false,"RightButtonDown":false,"MiddleButtonDown":false,"EventType":0,"EventTimeInTicks":637195298240941222},{"PositionX":167,"PositionY":521,"LeftButtonDown":false,"RightButtonDown":false,"MiddleButtonDown":false,"EventType":0,"EventTimeInTicks":637195298241111182},{"PositionX":167,"PositionY":545,"LeftButtonDown":false,"RightButtonDown":false,"MiddleButtonDown":false,"EventType":0,"EventTimeInTicks":637195298241251237},{"PositionX":171,"PositionY":588,"LeftButtonDown":false,"RightButtonDown":false,"MiddleButtonDown":false,"EventType":0,"EventTimeInTicks":637195298241421180},{"PositionX":172,"PositionY":622,"LeftButtonDown":false,"RightButtonDown":false,"MiddleButtonDown":false,"EventType":0,"EventTimeInTicks":637195298241621164},{"PositionX":175,"PositionY":647,"LeftButtonDown":false,"RightButtonDown":false,"MiddleButtonDown":false,"EventType":0,"EventTimeInTicks":637195298241701204},{"PositionX":176,"PositionY":666,"LeftButtonDown":false,"RightButtonDown":false,"MiddleButtonDown":false,"EventType":0,"EventTimeInTicks":637195298241871193},{"PositionX":176,"PositionY":677,"LeftButtonDown":false,"RightButtonDown":false,"MiddleButtonDown":false,"EventType":0,"EventTimeInTicks":637195298242041215},{"PositionX":174,"PositionY":687,"LeftButtonDown":false,"RightButtonDown":false,"MiddleButtonDown":false,"EventType":0,"EventTimeInTicks":637195298242171191},{"PositionX":172,"PositionY":697,"LeftButtonDown":false,"RightButtonDown":false,"MiddleButtonDown":false,"EventType":0,"EventTimeInTicks":637195298242331170},{"PositionX":171,"PositionY":702,"LeftButtonDown":false,"RightButtonDown":false,"MiddleButtonDown":false,"EventType":0,"EventTimeInTicks":637195298242491177},{"PositionX":165,"PositionY":715,"LeftButtonDown":false,"RightButtonDown":false,"MiddleButtonDown":false,"EventType":0,"EventTimeInTicks":637195298242661200},{"PositionX":159,"PositionY":721,"LeftButtonDown":false,"RightButtonDown":false,"MiddleButtonDown":false,"EventType":0,"EventTimeInTicks":637195298242821310},{"PositionX":153,"PositionY":725,"LeftButtonDown":false,"RightButtonDown":false,"MiddleButtonDown":false,"EventType":0,"EventTimeInTicks":637195298242991167},{"PositionX":148,"PositionY":728,"LeftButtonDown":false,"RightButtonDown":false,"MiddleButtonDown":false,"EventType":0,"EventTimeInTicks":637195298243101176},{"PositionX":141,"PositionY":731,"LeftButtonDown":false,"RightButtonDown":false,"MiddleButtonDown":false,"EventType":0,"EventTimeInTicks":637195298243291153},{"PositionX":136,"PositionY":734,"LeftButtonDown":false,"RightButtonDown":false,"MiddleButtonDown":false,"EventType":0,"EventTimeInTicks":637195298243441182},{"PositionX":131,"PositionY":736,"LeftButtonDown":false,"RightButtonDown":false,"MiddleButtonDown":false,"EventType":0,"EventTimeInTicks":637195298243561154},{"PositionX":126,"PositionY":737,"LeftButtonDown":false,"RightButtonDown":false,"MiddleButtonDown":false,"EventType":0,"EventTimeInTicks":637195298243741147},{"PositionX":119,"PositionY":742,"LeftButtonDown":false,"RightButtonDown":false,"MiddleButtonDown":false,"EventType":0,"EventTimeInTicks":637195298243921152},{"PositionX":113,"PositionY":747,"LeftButtonDown":false,"RightButtonDown":false,"MiddleButtonDown":false,"EventType":0,"EventTimeInTicks":637195298244061157},{"PositionX":107,"PositionY":754,"LeftButtonDown":false,"RightButtonDown":false,"MiddleButtonDown":false,"EventType":0,"EventTimeInTicks":637195298244231204},{"PositionX":100,"PositionY":764,"LeftButtonDown":false,"RightButtonDown":false,"MiddleButtonDown":false,"EventType":0,"EventTimeInTicks":637195298244411163},{"PositionX":93,"PositionY":776,"LeftButtonDown":false,"RightButtonDown":false,"MiddleButtonDown":false,"EventType":0,"EventTimeInTicks":637195298244591184},{"PositionX":84,"PositionY":787,"LeftButtonDown":false,"RightButtonDown":false,"MiddleButtonDown":false,"EventType":0,"EventTimeInTicks":637195298244681232},{"PositionX":76,"PositionY":797,"LeftButtonDown":false,"RightButtonDown":false,"MiddleButtonDown":false,"EventType":0,"EventTimeInTicks":637195298244851167},{"PositionX":68,"PositionY":804,"LeftButtonDown":false,"RightButtonDown":false,"MiddleButtonDown":false,"EventType":0,"EventTimeInTicks":637195298244971145},{"PositionX":63,"PositionY":808,"LeftButtonDown":false,"RightButtonDown":false,"MiddleButtonDown":false,"EventType":0,"EventTimeInTicks":637195298245131143},{"PositionX":58,"PositionY":810,"LeftButtonDown":false,"RightButtonDown":false,"MiddleButtonDown":false,"EventType":0,"EventTimeInTicks":637195298245371159},{"PositionX":56,"PositionY":811,"LeftButtonDown":false,"RightButtonDown":false,"MiddleButtonDown":false,"EventType":0,"EventTimeInTicks":637195298245461263},{"PositionX":53,"PositionY":812,"LeftButtonDown":false,"RightButtonDown":false,"MiddleButtonDown":false,"EventType":0,"EventTimeInTicks":637195298245641161},{"PositionX":51,"PositionY":814,"LeftButtonDown":false,"RightButtonDown":false,"MiddleButtonDown":false,"EventType":0,"EventTimeInTicks":637195298245811153},{"PositionX":49,"PositionY":815,"LeftButtonDown":false,"RightButtonDown":false,"MiddleButtonDown":false,"EventType":0,"EventTimeInTicks":637195298245921165},{"PositionX":46,"PositionY":816,"LeftButtonDown":false,"RightButtonDown":false,"MiddleButtonDown":false,"EventType":0,"EventTimeInTicks":637195298246111282},{"PositionX":44,"PositionY":816,"LeftButtonDown":false,"RightButtonDown":false,"MiddleButtonDown":false,"EventType":0,"EventTimeInTicks":637195298246271128},{"PositionX":42,"PositionY":816,"LeftButtonDown":false,"RightButtonDown":false,"MiddleButtonDown":false,"EventType":0,"EventTimeInTicks":637195298246381137},{"PositionX":41,"PositionY":816,"LeftButtonDown":false,"RightButtonDown":false,"MiddleButtonDown":false,"EventType":0,"EventTimeInTicks":637195298246581149},{"PositionX":40,"PositionY":815,"LeftButtonDown":false,"RightButtonDown":false,"MiddleButtonDown":false,"EventType":0,"EventTimeInTicks":637195298247061162},{"PositionX":38,"PositionY":813,"LeftButtonDown":false,"RightButtonDown":false,"MiddleButtonDown":false,"EventType":0,"EventTimeInTicks":637195298247321124},{"PositionX":38,"PositionY":811,"LeftButtonDown":false,"RightButtonDown":false,"MiddleButtonDown":false,"EventType":0,"EventTimeInTicks":637195298247521158},{"PositionX":39,"PositionY":810,"LeftButtonDown":false,"RightButtonDown":false,"MiddleButtonDown":false,"EventType":0,"EventTimeInTicks":637195298250501103},{"PositionX":41,"PositionY":809,"LeftButtonDown":false,"RightButtonDown":false,"MiddleButtonDown":false,"EventType":0,"EventTimeInTicks":637195298250591272},{"PositionX":44,"PositionY":808,"LeftButtonDown":false,"RightButtonDown":false,"MiddleButtonDown":false,"EventType":0,"EventTimeInTicks":637195298250761120},{"PositionX":50,"PositionY":806,"LeftButtonDown":false,"RightButtonDown":false,"MiddleButtonDown":false,"EventType":0,"EventTimeInTicks":637195298250941133},{"PositionX":58,"PositionY":800,"LeftButtonDown":false,"RightButtonDown":false,"MiddleButtonDown":false,"EventType":0,"EventTimeInTicks":637195298251121117},{"PositionX":70,"PositionY":792,"LeftButtonDown":false,"RightButtonDown":false,"MiddleButtonDown":false,"EventType":0,"EventTimeInTicks":637195298251291107},{"PositionX":87,"PositionY":783,"LeftButtonDown":false,"RightButtonDown":false,"MiddleButtonDown":false,"EventType":0,"EventTimeInTicks":637195298251371096},{"PositionX":107,"PositionY":773,"LeftButtonDown":false,"RightButtonDown":false,"MiddleButtonDown":false,"EventType":0,"EventTimeInTicks":637195298251531117},{"PositionX":130,"PositionY":764,"LeftButtonDown":false,"RightButtonDown":false,"MiddleButtonDown":false,"EventType":0,"EventTimeInTicks":637195298251691132},{"PositionX":149,"PositionY":756,"LeftButtonDown":false,"RightButtonDown":false,"MiddleButtonDown":false,"EventType":0,"EventTimeInTicks":637195298251871095},{"PositionX":166,"PositionY":749,"LeftButtonDown":false,"RightButtonDown":false,"MiddleButtonDown":false,"EventType":0,"EventTimeInTicks":637195298252031127},{"PositionX":183,"PositionY":741,"LeftButtonDown":false,"RightButtonDown":false,"MiddleButtonDown":false,"EventType":0,"EventTimeInTicks":637195298252201223},{"PositionX":199,"PositionY":732,"LeftButtonDown":false,"RightButtonDown":false,"MiddleButtonDown":false,"EventType":0,"EventTimeInTicks":637195298252371131},{"PositionX":205,"PositionY":729,"LeftButtonDown":false,"RightButtonDown":false,"MiddleButtonDown":false,"EventType":0,"EventTimeInTicks":637195298252541098},{"PositionX":215,"PositionY":722,"LeftButtonDown":false,"RightButtonDown":false,"MiddleButtonDown":false,"EventType":0,"EventTimeInTicks":637195298252621100},{"PositionX":218,"PositionY":721,"LeftButtonDown":false,"RightButtonDown":false,"MiddleButtonDown":false,"EventType":0,"EventTimeInTicks":637195298252801096},{"PositionX":219,"PositionY":721,"LeftButtonDown":false,"RightButtonDown":false,"MiddleButtonDown":false,"EventType":0,"EventTimeInTicks":637195298253561125},{"PositionX":221,"PositionY":720,"LeftButtonDown":false,"RightButtonDown":false,"MiddleButtonDown":false,"EventType":0,"EventTimeInTicks":637195298253731099},{"PositionX":224,"PositionY":719,"LeftButtonDown":false,"RightButtonDown":false,"MiddleButtonDown":false,"EventType":0,"EventTimeInTicks":637195298253861119},{"PositionX":225,"PositionY":718,"LeftButtonDown":false,"RightButtonDown":false,"MiddleButtonDown":false,"EventType":0,"EventTimeInTicks":637195298262461026},{"Key":27,"IsShift":false,"IsAlt":false,"IsCtrl":false,"IsWin":false,"EventType":1,"EventTimeInTicks":637195298263391010}]